amd_taichi/__init__.py
test_amd_taichi-0.0.1.dist-info/METADATA
test_amd_taichi-0.0.1.dist-info/WHEEL
test_amd_taichi-0.0.1.dist-info/top_level.txt
test_amd_taichi-0.0.1.dist-info/RECORD
