Metadata-Version: 2.4
Name: test-amd-taichi
Version: 0.0.1
Summary: The Taichi Programming Language
Author-email: AMD <support@amd.com>
License: See LICENSE file
Project-URL: Homepage, https://github.com/taichi-dev/taichi
Requires-Python: >=3.8
